Workbook

Sheet Aktion vs. ohne Aktion
A1: Halloween-Aktion: Gewinn mit vs. ohne Aktion
A2: Aktionszeitraum Do 29.10. 18:00 – So 1.11. 23:59. Hochgerechnet aus den echten Bestellungen der letzten 30 Tage. Gewinn nach Einkauf, Partner-Provision, DHL und Verpackung (vor Fixkosten/Werbung).
A4: Annahmen für die Szenarien (gelb = ändern zum Durchspielen)
A5: Anteil der Kunden mit 1–2 Flaschen, die auf 3 auffüllen | B5: 0.5
A6: Zusätzliche Bestellungen durch die Aktion | B6: 1
A8: Ergebnis
B9: Bestellungen | C9: Umsatz | D9: Gewinn | E9: Gewinn je Bestellung | F9: Unterschied zu ohne Aktion
A10: Ohne Aktion (normales Wochenende) | B10: ='Bestellungen 30 Tage'!B57*Annahmen!$B$21/Annahmen!$B$20 -> 5.525 | C10: ='Bestellungen 30 Tage'!E56*Annahmen!$B$21/Annahmen!$B$20 -> 983.36983 | D10: ='Bestellungen 30 Tage'!F56*Annahmen!$B$21/Annahmen!$B$20 -> 691.8145 | E10: =D10/B10 -> 125.21529
A11: Halloween – gleiche Kunden, gleiche Mengen | B11: =B10 -> 5.525 | C11: ='Bestellungen 30 Tage'!G56*Annahmen!$B$21/Annahmen!$B$20 -> 992.63883 | D11: ='Bestellungen 30 Tage'!I56*Annahmen!$B$21/Annahmen!$B$20 -> 669.721 | E11: =D11/B11 -> 121.21647 | F11: =D11-$D$10 -> -22.0935
A12: Halloween – mit Auffüllen (B5) | B12: =B10 -> 5.525 | D12: =('Bestellungen 30 Tage'!I56+$B$5*('Bestellungen 30 Tage'!J56-'Bestellungen 30 Tage'!I56))*Annahmen!$B$21/Annahmen!$B$20 -> 723.372 | E12: =D12/B12 -> 130.92706 | F12: =D12-$D$10 -> 31.5575
A13: Halloween – mit Auffüllen (B5) und mehr Bestellungen (B6) | B13: =B10*(1+$B$6) -> 11.05 | D13: =D12*(1+$B$6) -> 1446.744 | E13: =D13/B13 -> 130.92706 | F13: =D13-$D$10 -> 754.9295
A15: Szenario-Tabelle: Unterschied im Gewinn zu „ohne Aktion“
A16: Auffüllen auf 3 Flaschen → | B16: 0 % | C16: 50 % | D16: 100 %
A17: Anteil auffüllen: | B17: 0 | C17: 0.5 | D17: 1
A18: 0 | B18: =('Bestellungen 30 Tage'!I56+B$17*('Bestellungen 30 Tage'!J56-'Bestellungen 30 Tage'!I56))*Annahmen!$B$21/Annahmen!$B$20*(1+$A18)-$D$10 -> -22.0935 | C18: =('Bestellungen 30 Tage'!I56+C$17*('Bestellungen 30 Tage'!J56-'Bestellungen 30 Tage'!I56))*Annahmen!$B$21/Annahmen!$B$20*(1+$A18)-$D$10 -> 31.5575 | D18: =('Bestellungen 30 Tage'!I56+D$17*('Bestellungen 30 Tage'!J56-'Bestellungen 30 Tage'!I56))*Annahmen!$B$21/Annahmen!$B$20*(1+$A18)-$D$10 -> 85.2085
A19: 0.25 | B19: =('Bestellungen 30 Tage'!I56+B$17*('Bestellungen 30 Tage'!J56-'Bestellungen 30 Tage'!I56))*Annahmen!$B$21/Annahmen!$B$20*(1+$A19)-$D$10 -> 145.33675 | C19: =('Bestellungen 30 Tage'!I56+C$17*('Bestellungen 30 Tage'!J56-'Bestellungen 30 Tage'!I56))*Annahmen!$B$21/Annahmen!$B$20*(1+$A19)-$D$10 -> 212.4005 | D19: =('Bestellungen 30 Tage'!I56+D$17*('Bestellungen 30 Tage'!J56-'Bestellungen 30 Tage'!I56))*Annahmen!$B$21/Annahmen!$B$20*(1+$A19)-$D$10 -> 279.46425
A20: 0.5 | B20: =('Bestellungen 30 Tage'!I56+B$17*('Bestellungen 30 Tage'!J56-'Bestellungen 30 Tage'!I56))*Annahmen!$B$21/Annahmen!$B$20*(1+$A20)-$D$10 -> 312.767 | C20: =('Bestellungen 30 Tage'!I56+C$17*('Bestellungen 30 Tage'!J56-'Bestellungen 30 Tage'!I56))*Annahmen!$B$21/Annahmen!$B$20*(1+$A20)-$D$10 -> 393.2435 | D20: =('Bestellungen 30 Tage'!I56+D$17*('Bestellungen 30 Tage'!J56-'Bestellungen 30 Tage'!I56))*Annahmen!$B$21/Annahmen!$B$20*(1+$A20)-$D$10 -> 473.72
A21: 1 | B21: =('Bestellungen 30 Tage'!I56+B$17*('Bestellungen 30 Tage'!J56-'Bestellungen 30 Tage'!I56))*Annahmen!$B$21/Annahmen!$B$20*(1+$A21)-$D$10 -> 647.6275 | C21: =('Bestellungen 30 Tage'!I56+C$17*('Bestellungen 30 Tage'!J56-'Bestellungen 30 Tage'!I56))*Annahmen!$B$21/Annahmen!$B$20*(1+$A21)-$D$10 -> 754.9295 | D21: =('Bestellungen 30 Tage'!I56+D$17*('Bestellungen 30 Tage'!J56-'Bestellungen 30 Tage'!I56))*Annahmen!$B$21/Annahmen!$B$20*(1+$A21)-$D$10 -> 862.2315
A22: 2 | B22: =('Bestellungen 30 Tage'!I56+B$17*('Bestellungen 30 Tage'!J56-'Bestellungen 30 Tage'!I56))*Annahmen!$B$21/Annahmen!$B$20*(1+$A22)-$D$10 -> 1317.3485 | C22: =('Bestellungen 30 Tage'!I56+C$17*('Bestellungen 30 Tage'!J56-'Bestellungen 30 Tage'!I56))*Annahmen!$B$21/Annahmen!$B$20*(1+$A22)-$D$10 -> 1478.3015 | D22: =('Bestellungen 30 Tage'!I56+D$17*('Bestellungen 30 Tage'!J56-'Bestellungen 30 Tage'!I56))*Annahmen!$B$21/Annahmen!$B$20*(1+$A22)-$D$10 -> 1639.2545
A24: Break-even
A25: Zusätzliche Bestellungen, ab denen sich die Aktion lohnt (ohne Auffüllen) | B25: =MAX(0,-F11/E11) -> 0.18226483
A27: So liest man das
A28: • „Ohne Aktion“ = durchschnittliches Wochenende (3¼ Tage) aus den letzten 30 Tagen.
A29: • „Gleiche Kunden, gleiche Mengen“: Bestellungen wie bisher, nur mit Halloween-Preisen. Etwas weniger Gewinn, weil wer ohnehin 3+ Flaschen kauft, jetzt eine gratis bekommt und Partner 5 % mehr Provision erhalten.
A30: • Jede zusätzliche Bestellung bringt im Schnitt den Gewinn aus Spalte E – schon 1 zusätzliche Bestellung gleicht den Nachteil aus.
A31: • Einkaufspreise sind sehr niedrig (Retatrutide 10 mg ≈ 8,46 €), daher bleibt auch mit Gratis-Flasche viel Marge.
A32: • Details pro Warenkorb: Blatt „Warenkorb-Rechnung“. Grundlage: Blatt „Bestellungen 30 Tage“. Alle Annahmen: Blatt „Annahmen“.

Sheet Annahmen
A1: Annahmen (blaue Werte können geändert werden – alles andere rechnet automatisch)
A2: Annahme | B2: Wert | C2: Quelle / Hinweis
A3: Preis Retatrutide 10 mg (VK) | B3: 74.9 | C3: Shop-Preis, regulär
A4: Einkauf Retatrutide 10 mg in $ | B4: 9.5 | C4: Lieferanten-Preis pro Flasche (Angabe Inhaber)
A5: Wechselkurs $ → € | B5: 0.8903 | C5: Tageskurs open.er-api.com, 22.10.2026
A6: Einkauf Retatrutide 10 mg in € | B6: =B4*B5 -> 8.45785 | C6: Formel
A7: Partner-Provision normal | B7: 0.2 | C7: Vereinbarter Satz der aktiven Partnerin (alle Partner-Bestellungen der letzten 30 Tage)
A8: Halloween-Bonus Provision | B8: 0.05 | C8: Zusätzlich während der Aktion
A9: Partner-Rabatt für Kunden (normal) | B9: 0.1 | C9: 10 % Empfehlungs-Rabatt über Partner-Link/-Code
A10: Mengenrabatt ab 3 Flaschen | B10: 0.1 | C10: Shop-Regel
A11: Mengenrabatt ab 5 Flaschen | B11: 0.15 | C11: Shop-Regel
A12: Mengenrabatt ab 10 Flaschen | B12: 0.2 | C12: Shop-Regel
A13: Versand, den der Kunde zahlt | B13: 4.9 | C13: DE, unter Gratisversand-Grenze
A14: Gratisversand ab (Warenwert) | B14: 150 | C14: DE
A15: DHL-Kosten pro Paket | B15: 6.19 | C15: Angabe Inhaber
A16: Verpackung pro Paket | B16: 0.2 | C16: 100 Stk = 20 €
A17: Geschenk ab 200 € (Injektionskit) – Einkauf | B17: 4.0346 | C17: 10 Spritzen + 1 Bac Water + Tupfer
A18: Geschenk ab 350 € (GHK-Cu 50 mg) – Einkauf | B18: 2.938 | C18: 3,30 $
A19: Geschenk ab 500 € (Retatrutide 10 mg) – Einkauf | B19: =B6 -> 8.45785 | C19: Formel
A20: Tage im Vergleichszeitraum | B20: 30 | C20: Bestellungen der letzten 30 Tage (Blatt „Bestellungen 30 Tage“)
A21: Dauer der Aktion in Tagen | B21: 3.25 | C21: Do 29.10. 18:00 bis So 1.11. 23:59

Sheet Warenkorb-Rechnung
A1: Was bleibt pro Bestellung übrig? Beispiel Retatrutide 10 mg
A2: Gewinn = Umsatz − Einkauf der Flaschen − Einkauf Geschenke − Partner-Provision − DHL − Verpackung (vor Fixkosten/Werbung)
A4: Kunde | B4: Flaschen | C4: Angebot | D4: Warenwert regulär | E4: Kunde zahlt für Ware | F4: Versand (Kunde zahlt) | G4: Umsatz gesamt | H4: Einkauf Flaschen | I4: Einkauf Geschenke | J4: Partner-Provision | K4: DHL + Verpackung | L4: Gewinn | M4: Gewinn-Unterschied zu normal
A5: Über Partner | B5: 1 | C5: Normal | D5: =B5*Annahmen!$B$3 -> 74.9 | E5: =(IF(B5>=10,10*Annahmen!$B$3*(1-Annahmen!$B$12)+(B5-10)*Annahmen!$B$3,IF(B5>=5,5*Annahmen!$B$3*(1-Annahmen!$B$11)+(B5-5)*Annahmen!$B$3,IF(B5>=3,3*Annahmen!$B$3*(1-Annahmen!$B$10)+(B5-3)*Annahmen!$B$3,B5*Annahmen!$B$3))))*(1-Annahmen!$B$9) -> 67.41 | F5: =IF(E5>=Annahmen!$B$14,0,Annahmen!$B$13) -> 4.9 | G5: =E5+F5 -> 72.31 | H5: =B5*Annahmen!$B$6 -> 8.45785 | I5: =IF(E5>=200,Annahmen!$B$17,0)+IF(E5>=350,Annahmen!$B$18,0)+IF(E5>=500,Annahmen!$B$19,0) -> 0 | J5: =E5*Annahmen!$B$7 -> 13.482 | K5: =Annahmen!$B$15+Annahmen!$B$16 -> 6.39 | L5: =G5-H5-I5-J5-K5 -> 43.98015
A6: Über Partner | B6: 1 | C6: Halloween | D6: =B6*Annahmen!$B$3 -> 74.9 | E6: =(B6-INT(B6/3))*Annahmen!$B$3 -> 74.9 | F6: =IF(E6>=Annahmen!$B$14,0,Annahmen!$B$13) -> 4.9 | G6: =E6+F6 -> 79.8 | H6: =B6*Annahmen!$B$6 -> 8.45785 | I6: =IF(E6>=200,Annahmen!$B$17,0)+IF(E6>=350,Annahmen!$B$18,0)+IF(E6>=500,Annahmen!$B$19,0) -> 0 | J6: =E6*(Annahmen!$B$7+Annahmen!$B$8) -> 18.725 | K6: =Annahmen!$B$15+Annahmen!$B$16 -> 6.39 | L6: =G6-H6-I6-J6-K6 -> 46.22715 | M6: =L6-L5 -> 2.247
A7: Über Partner | B7: 1 | C7: Halloween + Bestpreis-Regel | D7: =B7*Annahmen!$B$3 -> 74.9 | E7: =MIN((IF(B7>=10,10*Annahmen!$B$3*(1-Annahmen!$B$12)+(B7-10)*Annahmen!$B$3,IF(B7>=5,5*Annahmen!$B$3*(1-Annahmen!$B$11)+(B7-5)*Annahmen!$B$3,IF(B7>=3,3*Annahmen!$B$3*(1-Annahmen!$B$10)+(B7-3)*Annahmen!$B$3,B7*Annahmen!$B$3))))*(1-Annahmen!$B$9),(B7-INT(B7/3))*Annahmen!$B$3) -> 67.41 | F7: =IF(E7>=Annahmen!$B$14,0,Annahmen!$B$13) -> 4.9 | G7: =E7+F7 -> 72.31 | H7: =B7*Annahmen!$B$6 -> 8.45785 | I7: =IF(E7>=200,Annahmen!$B$17,0)+IF(E7>=350,Annahmen!$B$18,0)+IF(E7>=500,Annahmen!$B$19,0) -> 0 | J7: =E7*(Annahmen!$B$7+Annahmen!$B$8) -> 16.8525 | K7: =Annahmen!$B$15+Annahmen!$B$16 -> 6.39 | L7: =G7-H7-I7-J7-K7 -> 40.60965 | M7: =L7-L5 -> -3.3705
A8: Über Partner | B8: 2 | C8: Normal | D8: =B8*Annahmen!$B$3 -> 149.8 | E8: =(IF(B8>=10,10*Annahmen!$B$3*(1-Annahmen!$B$12)+(B8-10)*Annahmen!$B$3,IF(B8>=5,5*Annahmen!$B$3*(1-Annahmen!$B$11)+(B8-5)*Annahmen!$B$3,IF(B8>=3,3*Annahmen!$B$3*(1-Annahmen!$B$10)+(B8-3)*Annahmen!$B$3,B8*Annahmen!$B$3))))*(1-Annahmen!$B$9) -> 134.82 | F8: =IF(E8>=Annahmen!$B$14,0,Annahmen!$B$13) -> 4.9 | G8: =E8+F8 -> 139.72 | H8: =B8*Annahmen!$B$6 -> 16.9157 | I8: =IF(E8>=200,Annahmen!$B$17,0)+IF(E8>=350,Annahmen!$B$18,0)+IF(E8>=500,Annahmen!$B$19,0) -> 0 | J8: =E8*Annahmen!$B$7 -> 26.964 | K8: =Annahmen!$B$15+Annahmen!$B$16 -> 6.39 | L8: =G8-H8-I8-J8-K8 -> 89.4503
A9: Über Partner | B9: 2 | C9: Halloween | D9: =B9*Annahmen!$B$3 -> 149.8 | E9: =(B9-INT(B9/3))*Annahmen!$B$3 -> 149.8 | F9: =IF(E9>=Annahmen!$B$14,0,Annahmen!$B$13) -> 4.9 | G9: =E9+F9 -> 154.7 | H9: =B9*Annahmen!$B$6 -> 16.9157 | I9: =IF(E9>=200,Annahmen!$B$17,0)+IF(E9>=350,Annahmen!$B$18,0)+IF(E9>=500,Annahmen!$B$19,0) -> 0 | J9: =E9*(Annahmen!$B$7+Annahmen!$B$8) -> 37.45 | K9: =Annahmen!$B$15+Annahmen!$B$16 -> 6.39 | L9: =G9-H9-I9-J9-K9 -> 93.9443 | M9: =L9-L8 -> 4.494
A10: Über Partner | B10: 2 | C10: Halloween + Bestpreis-Regel | D10: =B10*Annahmen!$B$3 -> 149.8 | E10: =MIN((IF(B10>=10,10*Annahmen!$B$3*(1-Annahmen!$B$12)+(B10-10)*Annahmen!$B$3,IF(B10>=5,5*Annahmen!$B$3*(1-Annahmen!$B$11)+(B10-5)*Annahmen!$B$3,IF(B10>=3,3*Annahmen!$B$3*(1-Annahmen!$B$10)+(B10-3)*Annahmen!$B$3,B10*Annahmen!$B$3))))*(1-Annahmen!$B$9),(B10-INT(B10/3))*Annahmen!$B$3) -> 134.82 | F10: =IF(E10>=Annahmen!$B$14,0,Annahmen!$B$13) -> 4.9 | G10: =E10+F10 -> 139.72 | H10: =B10*Annahmen!$B$6 -> 16.9157 | I10: =IF(E10>=200,Annahmen!$B$17,0)+IF(E10>=350,Annahmen!$B$18,0)+IF(E10>=500,Annahmen!$B$19,0) -> 0 | J10: =E10*(Annahmen!$B$7+Annahmen!$B$8) -> 33.705 | K10: =Annahmen!$B$15+Annahmen!$B$16 -> 6.39 | L10: =G10-H10-I10-J10-K10 -> 82.7093 | M10: =L10-L8 -> -6.741
A11: Über Partner | B11: 3 | C11: Normal | D11: =B11*Annahmen!$B$3 -> 224.7 | E11: =(IF(B11>=10,10*Annahmen!$B$3*(1-Annahmen!$B$12)+(B11-10)*Annahmen!$B$3,IF(B11>=5,5*Annahmen!$B$3*(1-Annahmen!$B$11)+(B11-5)*Annahmen!$B$3,IF(B11>=3,3*Annahmen!$B$3*(1-Annahmen!$B$10)+(B11-3)*Annahmen!$B$3,B11*Annahmen!$B$3))))*(1-Annahmen!$B$9) -> 182.007 | F11: =IF(E11>=Annahmen!$B$14,0,Annahmen!$B$13) -> 0 | G11: =E11+F11 -> 182.007 | H11: =B11*Annahmen!$B$6 -> 25.37355 | I11: =IF(E11>=200,Annahmen!$B$17,0)+IF(E11>=350,Annahmen!$B$18,0)+IF(E11>=500,Annahmen!$B$19,0) -> 0 | J11: =E11*Annahmen!$B$7 -> 36.4014 | K11: =Annahmen!$B$15+Annahmen!$B$16 -> 6.39 | L11: =G11-H11-I11-J11-K11 -> 113.84205
A12: Über Partner | B12: 3 | C12: Halloween | D12: =B12*Annahmen!$B$3 -> 224.7 | E12: =(B12-INT(B12/3))*Annahmen!$B$3 -> 149.8 | F12: =IF(E12>=Annahmen!$B$14,0,Annahmen!$B$13) -> 4.9 | G12: =E12+F12 -> 154.7 | H12: =B12*Annahmen!$B$6 -> 25.37355 | I12: =IF(E12>=200,Annahmen!$B$17,0)+IF(E12>=350,Annahmen!$B$18,0)+IF(E12>=500,Annahmen!$B$19,0) -> 0 | J12: =E12*(Annahmen!$B$7+Annahmen!$B$8) -> 37.45 | K12: =Annahmen!$B$15+Annahmen!$B$16 -> 6.39 | L12: =G12-H12-I12-J12-K12 -> 85.48645 | M12: =L12-L11 -> -28.3556
A13: Über Partner | B13: 3 | C13: Halloween + Bestpreis-Regel | D13: =B13*Annahmen!$B$3 -> 224.7 | E13: =MIN((IF(B13>=10,10*Annahmen!$B$3*(1-Annahmen!$B$12)+(B13-10)*Annahmen!$B$3,IF(B13>=5,5*Annahmen!$B$3*(1-Annahmen!$B$11)+(B13-5)*Annahmen!$B$3,IF(B13>=3,3*Annahmen!$B$3*(1-Annahmen!$B$10)+(B13-3)*Annahmen!$B$3,B13*Annahmen!$B$3))))*(1-Annahmen!$B$9),(B13-INT(B13/3))*Annahmen!$B$3) -> 149.8 | F13: =IF(E13>=Annahmen!$B$14,0,Annahmen!$B$13) -> 4.9 | G13: =E13+F13 -> 154.7 | H13: =B13*Annahmen!$B$6 -> 25.37355 | I13: =IF(E13>=200,Annahmen!$B$17,0)+IF(E13>=350,Annahmen!$B$18,0)+IF(E13>=500,Annahmen!$B$19,0) -> 0 | J13: =E13*(Annahmen!$B$7+Annahmen!$B$8) -> 37.45 | K13: =Annahmen!$B$15+Annahmen!$B$16 -> 6.39 | L13: =G13-H13-I13-J13-K13 -> 85.48645 | M13: =L13-L11 -> -28.3556
A14: Über Partner | B14: 6 | C14: Normal | D14: =B14*Annahmen!$B$3 -> 449.4 | E14: =(IF(B14>=10,10*Annahmen!$B$3*(1-Annahmen!$B$12)+(B14-10)*Annahmen!$B$3,IF(B14>=5,5*Annahmen!$B$3*(1-Annahmen!$B$11)+(B14-5)*Annahmen!$B$3,IF(B14>=3,3*Annahmen!$B$3*(1-Annahmen!$B$10)+(B14-3)*Annahmen!$B$3,B14*Annahmen!$B$3))))*(1-Annahmen!$B$9) -> 353.9025 | F14: =IF(E14>=Annahmen!$B$14,0,Annahmen!$B$13) -> 0 | G14: =E14+F14 -> 353.9025 | H14: =B14*Annahmen!$B$6 -> 50.7471 | I14: =IF(E14>=200,Annahmen!$B$17,0)+IF(E14>=350,Annahmen!$B$18,0)+IF(E14>=500,Annahmen!$B$19,0) -> 6.9726 | J14: =E14*Annahmen!$B$7 -> 70.7805 | K14: =Annahmen!$B$15+Annahmen!$B$16 -> 6.39 | L14: =G14-H14-I14-J14-K14 -> 219.0123
A15: Über Partner | B15: 6 | C15: Halloween | D15: =B15*Annahmen!$B$3 -> 449.4 | E15: =(B15-INT(B15/3))*Annahmen!$B$3 -> 299.6 | F15: =IF(E15>=Annahmen!$B$14,0,Annahmen!$B$13) -> 0 | G15: =E15+F15 -> 299.6 | H15: =B15*Annahmen!$B$6 -> 50.7471 | I15: =IF(E15>=200,Annahmen!$B$17,0)+IF(E15>=350,Annahmen!$B$18,0)+IF(E15>=500,Annahmen!$B$19,0) -> 4.0346 | J15: =E15*(Annahmen!$B$7+Annahmen!$B$8) -> 74.9 | K15: =Annahmen!$B$15+Annahmen!$B$16 -> 6.39 | L15: =G15-H15-I15-J15-K15 -> 163.5283 | M15: =L15-L14 -> -55.484
A16: Über Partner | B16: 6 | C16: Halloween + Bestpreis-Regel | D16: =B16*Annahmen!$B$3 -> 449.4 | E16: =MIN((IF(B16>=10,10*Annahmen!$B$3*(1-Annahmen!$B$12)+(B16-10)*Annahmen!$B$3,IF(B16>=5,5*Annahmen!$B$3*(1-Annahmen!$B$11)+(B16-5)*Annahmen!$B$3,IF(B16>=3,3*Annahmen!$B$3*(1-Annahmen!$B$10)+(B16-3)*Annahmen!$B$3,B16*Annahmen!$B$3))))*(1-Annahmen!$B$9),(B16-INT(B16/3))*Annahmen!$B$3) -> 299.6 | F16: =IF(E16>=Annahmen!$B$14,0,Annahmen!$B$13) -> 0 | G16: =E16+F16 -> 299.6 | H16: =B16*Annahmen!$B$6 -> 50.7471 | I16: =IF(E16>=200,Annahmen!$B$17,0)+IF(E16>=350,Annahmen!$B$18,0)+IF(E16>=500,Annahmen!$B$19,0) -> 4.0346 | J16: =E16*(Annahmen!$B$7+Annahmen!$B$8) -> 74.9 | K16: =Annahmen!$B$15+Annahmen!$B$16 -> 6.39 | L16: =G16-H16-I16-J16-K16 -> 163.5283 | M16: =L16-L14 -> -55.484
A17: Über Partner | B17: 9 | C17: Normal | D17: =B17*Annahmen!$B$3 -> 674.1 | E17: =(IF(B17>=10,10*Annahmen!$B$3*(1-Annahmen!$B$12)+(B17-10)*Annahmen!$B$3,IF(B17>=5,5*Annahmen!$B$3*(1-Annahmen!$B$11)+(B17-5)*Annahmen!$B$3,IF(B17>=3,3*Annahmen!$B$3*(1-Annahmen!$B$10)+(B17-3)*Annahmen!$B$3,B17*Annahmen!$B$3))))*(1-Annahmen!$B$9) -> 556.1325 | F17: =IF(E17>=Annahmen!$B$14,0,Annahmen!$B$13) -> 0 | G17: =E17+F17 -> 556.1325 | H17: =B17*Annahmen!$B$6 -> 76.12065 | I17: =IF(E17>=200,Annahmen!$B$17,0)+IF(E17>=350,Annahmen!$B$18,0)+IF(E17>=500,Annahmen!$B$19,0) -> 15.43045 | J17: =E17*Annahmen!$B$7 -> 111.2265 | K17: =Annahmen!$B$15+Annahmen!$B$16 -> 6.39 | L17: =G17-H17-I17-J17-K17 -> 346.9649
A18: Über Partner | B18: 9 | C18: Halloween | D18: =B18*Annahmen!$B$3 -> 674.1 | E18: =(B18-INT(B18/3))*Annahmen!$B$3 -> 449.4 | F18: =IF(E18>=Annahmen!$B$14,0,Annahmen!$B$13) -> 0 | G18: =E18+F18 -> 449.4 | H18: =B18*Annahmen!$B$6 -> 76.12065 | I18: =IF(E18>=200,Annahmen!$B$17,0)+IF(E18>=350,Annahmen!$B$18,0)+IF(E18>=500,Annahmen!$B$19,0) -> 6.9726 | J18: =E18*(Annahmen!$B$7+Annahmen!$B$8) -> 112.35 | K18: =Annahmen!$B$15+Annahmen!$B$16 -> 6.39 | L18: =G18-H18-I18-J18-K18 -> 247.56675 | M18: =L18-L17 -> -99.39815
A19: Über Partner | B19: 9 | C19: Halloween + Bestpreis-Regel | D19: =B19*Annahmen!$B$3 -> 674.1 | E19: =MIN((IF(B19>=10,10*Annahmen!$B$3*(1-Annahmen!$B$12)+(B19-10)*Annahmen!$B$3,IF(B19>=5,5*Annahmen!$B$3*(1-Annahmen!$B$11)+(B19-5)*Annahmen!$B$3,IF(B19>=3,3*Annahmen!$B$3*(1-Annahmen!$B$10)+(B19-3)*Annahmen!$B$3,B19*Annahmen!$B$3))))*(1-Annahmen!$B$9),(B19-INT(B19/3))*Annahmen!$B$3) -> 449.4 | F19: =IF(E19>=Annahmen!$B$14,0,Annahmen!$B$13) -> 0 | G19: =E19+F19 -> 449.4 | H19: =B19*Annahmen!$B$6 -> 76.12065 | I19: =IF(E19>=200,Annahmen!$B$17,0)+IF(E19>=350,Annahmen!$B$18,0)+IF(E19>=500,Annahmen!$B$19,0) -> 6.9726 | J19: =E19*(Annahmen!$B$7+Annahmen!$B$8) -> 112.35 | K19: =Annahmen!$B$15+Annahmen!$B$16 -> 6.39 | L19: =G19-H19-I19-J19-K19 -> 247.56675 | M19: =L19-L17 -> -99.39815
A20: Ohne Partner | B20: 1 | C20: Normal | D20: =B20*Annahmen!$B$3 -> 74.9 | E20: =(IF(B20>=10,10*Annahmen!$B$3*(1-Annahmen!$B$12)+(B20-10)*Annahmen!$B$3,IF(B20>=5,5*Annahmen!$B$3*(1-Annahmen!$B$11)+(B20-5)*Annahmen!$B$3,IF(B20>=3,3*Annahmen!$B$3*(1-Annahmen!$B$10)+(B20-3)*Annahmen!$B$3,B20*Annahmen!$B$3)))) -> 74.9 | F20: =IF(E20>=Annahmen!$B$14,0,Annahmen!$B$13) -> 4.9 | G20: =E20+F20 -> 79.8 | H20: =B20*Annahmen!$B$6 -> 8.45785 | I20: =IF(E20>=200,Annahmen!$B$17,0)+IF(E20>=350,Annahmen!$B$18,0)+IF(E20>=500,Annahmen!$B$19,0) -> 0 | J20: 0 | K20: =Annahmen!$B$15+Annahmen!$B$16 -> 6.39 | L20: =G20-H20-I20-J20-K20 -> 64.95215
A21: Ohne Partner | B21: 1 | C21: Halloween | D21: =B21*Annahmen!$B$3 -> 74.9 | E21: =(B21-INT(B21/3))*Annahmen!$B$3 -> 74.9 | F21: =IF(E21>=Annahmen!$B$14,0,Annahmen!$B$13) -> 4.9 | G21: =E21+F21 -> 79.8 | H21: =B21*Annahmen!$B$6 -> 8.45785 | I21: =IF(E21>=200,Annahmen!$B$17,0)+IF(E21>=350,Annahmen!$B$18,0)+IF(E21>=500,Annahmen!$B$19,0) -> 0 | J21: 0 | K21: =Annahmen!$B$15+Annahmen!$B$16 -> 6.39 | L21: =G21-H21-I21-J21-K21 -> 64.95215 | M21: =L21-L20 -> 0
A22: Ohne Partner | B22: 2 | C22: Normal | D22: =B22*Annahmen!$B$3 -> 149.8 | E22: =(IF(B22>=10,10*Annahmen!$B$3*(1-Annahmen!$B$12)+(B22-10)*Annahmen!$B$3,IF(B22>=5,5*Annahmen!$B$3*(1-Annahmen!$B$11)+(B22-5)*Annahmen!$B$3,IF(B22>=3,3*Annahmen!$B$3*(1-Annahmen!$B$10)+(B22-3)*Annahmen!$B$3,B22*Annahmen!$B$3)))) -> 149.8 | F22: =IF(E22>=Annahmen!$B$14,0,Annahmen!$B$13) -> 4.9 | G22: =E22+F22 -> 154.7 | H22: =B22*Annahmen!$B$6 -> 16.9157 | I22: =IF(E22>=200,Annahmen!$B$17,0)+IF(E22>=350,Annahmen!$B$18,0)+IF(E22>=500,Annahmen!$B$19,0) -> 0 | J22: 0 | K22: =Annahmen!$B$15+Annahmen!$B$16 -> 6.39 | L22: =G22-H22-I22-J22-K22 -> 131.3943
A23: Ohne Partner | B23: 2 | C23: Halloween | D23: =B23*Annahmen!$B$3 -> 149.8 | E23: =(B23-INT(B23/3))*Annahmen!$B$3 -> 149.8 | F23: =IF(E23>=Annahmen!$B$14,0,Annahmen!$B$13) -> 4.9 | G23: =E23+F23 -> 154.7 | H23: =B23*Annahmen!$B$6 -> 16.9157 | I23: =IF(E23>=200,Annahmen!$B$17,0)+IF(E23>=350,Annahmen!$B$18,0)+IF(E23>=500,Annahmen!$B$19,0) -> 0 | J23: 0 | K23: =Annahmen!$B$15+Annahmen!$B$16 -> 6.39 | L23: =G23-H23-I23-J23-K23 -> 131.3943 | M23: =L23-L22 -> 0
A24: Ohne Partner | B24: 3 | C24: Normal | D24: =B24*Annahmen!$B$3 -> 224.7 | E24: =(IF(B24>=10,10*Annahmen!$B$3*(1-Annahmen!$B$12)+(B24-10)*Annahmen!$B$3,IF(B24>=5,5*Annahmen!$B$3*(1-Annahmen!$B$11)+(B24-5)*Annahmen!$B$3,IF(B24>=3,3*Annahmen!$B$3*(1-Annahmen!$B$10)+(B24-3)*Annahmen!$B$3,B24*Annahmen!$B$3)))) -> 202.23 | F24: =IF(E24>=Annahmen!$B$14,0,Annahmen!$B$13) -> 0 | G24: =E24+F24 -> 202.23 | H24: =B24*Annahmen!$B$6 -> 25.37355 | I24: =IF(E24>=200,Annahmen!$B$17,0)+IF(E24>=350,Annahmen!$B$18,0)+IF(E24>=500,Annahmen!$B$19,0) -> 4.0346 | J24: 0 | K24: =Annahmen!$B$15+Annahmen!$B$16 -> 6.39 | L24: =G24-H24-I24-J24-K24 -> 166.43185
A25: Ohne Partner | B25: 3 | C25: Halloween | D25: =B25*Annahmen!$B$3 -> 224.7 | E25: =(B25-INT(B25/3))*Annahmen!$B$3 -> 149.8 | F25: =IF(E25>=Annahmen!$B$14,0,Annahmen!$B$13) -> 4.9 | G25: =E25+F25 -> 154.7 | H25: =B25*Annahmen!$B$6 -> 25.37355 | I25: =IF(E25>=200,Annahmen!$B$17,0)+IF(E25>=350,Annahmen!$B$18,0)+IF(E25>=500,Annahmen!$B$19,0) -> 0 | J25: 0 | K25: =Annahmen!$B$15+Annahmen!$B$16 -> 6.39 | L25: =G25-H25-I25-J25-K25 -> 122.93645 | M25: =L25-L24 -> -43.4954
A26: Ohne Partner | B26: 6 | C26: Normal | D26: =B26*Annahmen!$B$3 -> 449.4 | E26: =(IF(B26>=10,10*Annahmen!$B$3*(1-Annahmen!$B$12)+(B26-10)*Annahmen!$B$3,IF(B26>=5,5*Annahmen!$B$3*(1-Annahmen!$B$11)+(B26-5)*Annahmen!$B$3,IF(B26>=3,3*Annahmen!$B$3*(1-Annahmen!$B$10)+(B26-3)*Annahmen!$B$3,B26*Annahmen!$B$3)))) -> 393.225 | F26: =IF(E26>=Annahmen!$B$14,0,Annahmen!$B$13) -> 0 | G26: =E26+F26 -> 393.225 | H26: =B26*Annahmen!$B$6 -> 50.7471 | I26: =IF(E26>=200,Annahmen!$B$17,0)+IF(E26>=350,Annahmen!$B$18,0)+IF(E26>=500,Annahmen!$B$19,0) -> 6.9726 | J26: 0 | K26: =Annahmen!$B$15+Annahmen!$B$16 -> 6.39 | L26: =G26-H26-I26-J26-K26 -> 329.1153
A27: Ohne Partner | B27: 6 | C27: Halloween | D27: =B27*Annahmen!$B$3 -> 449.4 | E27: =(B27-INT(B27/3))*Annahmen!$B$3 -> 299.6 | F27: =IF(E27>=Annahmen!$B$14,0,Annahmen!$B$13) -> 0 | G27: =E27+F27 -> 299.6 | H27: =B27*Annahmen!$B$6 -> 50.7471 | I27: =IF(E27>=200,Annahmen!$B$17,0)+IF(E27>=350,Annahmen!$B$18,0)+IF(E27>=500,Annahmen!$B$19,0) -> 4.0346 | J27: 0 | K27: =Annahmen!$B$15+Annahmen!$B$16 -> 6.39 | L27: =G27-H27-I27-J27-K27 -> 238.4283 | M27: =L27-L26 -> -90.687
A28: Ohne Partner | B28: 9 | C28: Normal | D28: =B28*Annahmen!$B$3 -> 674.1 | E28: =(IF(B28>=10,10*Annahmen!$B$3*(1-Annahmen!$B$12)+(B28-10)*Annahmen!$B$3,IF(B28>=5,5*Annahmen!$B$3*(1-Annahmen!$B$11)+(B28-5)*Annahmen!$B$3,IF(B28>=3,3*Annahmen!$B$3*(1-Annahmen!$B$10)+(B28-3)*Annahmen!$B$3,B28*Annahmen!$B$3)))) -> 617.925 | F28: =IF(E28>=Annahmen!$B$14,0,Annahmen!$B$13) -> 0 | G28: =E28+F28 -> 617.925 | H28: =B28*Annahmen!$B$6 -> 76.12065 | I28: =IF(E28>=200,Annahmen!$B$17,0)+IF(E28>=350,Annahmen!$B$18,0)+IF(E28>=500,Annahmen!$B$19,0) -> 15.43045 | J28: 0 | K28: =Annahmen!$B$15+Annahmen!$B$16 -> 6.39 | L28: =G28-H28-I28-J28-K28 -> 519.9839
A29: Ohne Partner | B29: 9 | C29: Halloween | D29: =B29*Annahmen!$B$3 -> 674.1 | E29: =(B29-INT(B29/3))*Annahmen!$B$3 -> 449.4 | F29: =IF(E29>=Annahmen!$B$14,0,Annahmen!$B$13) -> 0 | G29: =E29+F29 -> 449.4 | H29: =B29*Annahmen!$B$6 -> 76.12065 | I29: =IF(E29>=200,Annahmen!$B$17,0)+IF(E29>=350,Annahmen!$B$18,0)+IF(E29>=500,Annahmen!$B$19,0) -> 6.9726 | J29: 0 | K29: =Annahmen!$B$15+Annahmen!$B$16 -> 6.39 | L29: =G29-H29-I29-J29-K29 -> 359.91675 | M29: =L29-L28 -> -160.06715
A31: Lesehilfe:
A32: • Normal: Mengenrabatt ab 3/5/10 Flaschen (nur auf die Flaschen der größten erreichten Staffel); Partner-Kunden bekommen zusätzlich 10 %.
A33: • Halloween: jede 3. Flasche gratis (die günstigste), kein Mengen- oder Partner-Rabatt auf Aktions-Flaschen, Partner bekommen 5 % mehr Provision.
A34: • Halloween + Bestpreis-Regel (Vorschlag): der Kunde bekommt automatisch das günstigere von beidem – niemand zahlt mehr als sonst.
A35: • Orange Zeilen = während der Aktion. Spalte M zeigt, wie viel mehr (+) oder weniger (−) pro Bestellung übrig bleibt.

Sheet Bestellungen 30 Tage
A1: Echte Bestellungen der letzten 30 Tage – tatsächlich vs. „wäre Halloween gewesen“
A2: Quelle: Shop-Datenbank, Stand 22.10.2026. Ohne Testbestellungen, Guthaben-Aufladungen und mit Guthaben bezahlte Abo-Lieferungen. Halloween-Spalten = gleiche Ware, nach Halloween-Regeln neu berechnet.
A4: Bestellung | B4: Über Partner | C4: Aktions-Flaschen | D4: davon gratis | E4: Umsatz tatsächlich | F4: Gewinn tatsächlich | G4: Umsatz Halloween | H4: Provision Halloween | I4: Gewinn Halloween | J4: Gewinn Halloween, wenn auf 3 Flaschen aufgefüllt
A5: #3297 | B5: Nein | C5: 1 | D5: 0 | E5: 164.7 | F5: 144.63 | G5: 164.7 | H5: 0 | I5: 144.63 | J5: 202.61
A6: #3292 | B6: Nein | C6: 1 | D6: 0 | E6: 72.31 | F6: 57.46 | G6: 79.8 | H6: 0 | I6: 64.95 | J6: 122.93
A7: #3291 | B7: Ja | C7: 0 | D7: 0 | E7: 305.91 | F7: 210.33 | G7: 305.91 | H7: 76.48 | I7: 195.04 | J7: 195.04
A8: #3290 | B8: Nein | C8: 0 | D8: 0 | E8: 24.7 | F8: 14.4 | G8: 24.7 | H8: 0 | I8: 14.4 | J8: 14.4
A9: #3288 | B9: Nein | C9: 1 | D9: 0 | E9: 99.04 | F9: 77.78 | G9: 106.53 | H9: 0 | I9: 85.27 | J9: 138.35
A10: #3287 | B10: Ja | C10: 0 | D10: 0 | E10: 238.41 | F10: 165.08 | G10: 238.41 | H10: 59.6 | I10: 153.16 | J10: 153.16
A11: #3286 | B11: Ja | C11: 1 | D11: 0 | E11: 91.44 | F11: 51.89 | G11: 103.83 | H11: 24.73 | I11: 57.84 | J11: 92.2
A12: #3285 | B12: Ja | C12: 2 | D12: 0 | E12: 134.82 | F12: 84.55 | G12: 154.7 | H12: 37.45 | I12: 93.95 | J12: 85.49
A13: #3283 | B13: Nein | C13: 3 | D13: 1 | E13: 337.56 | F13: 287.31 | G13: 285.13 | H13: 0 | I13: 234.88 | J13: 234.88
A14: #3281 | B14: Ja | C14: 1 | D14: 0 | E14: 87.43 | F14: 52.16 | G14: 94.92 | H14: 22.51 | I14: 53.65 | J14: 88.01
A15: #3280 | B15: Ja | C15: 1 | D15: 0 | E15: 78.52 | F15: 47.54 | G15: 86.01 | H15: 20.27 | I15: 49.47 | J15: 83.83
A16: #3279 | B16: Ja | C16: 1 | D16: 0 | E16: 87.43 | F16: 52.16 | G16: 94.92 | H16: 22.51 | I16: 53.65 | J16: 88.01
... A55: #3216 | B55: Nein | C55: 1 | D55: 0 | E55: 96.6 | F55: 77.84 | G55: 96.6 | H55: 0 | I55: 77.84 | J55: 130.92
A56: Summe | C56: =SUM(C5:C55) -> 51 | D56: =SUM(D5:D55) -> 5 | E56: =SUM(E5:E55) -> 9077.26 | F56: =SUM(F5:F55) -> 6385.98 | G56: =SUM(G5:G55) -> 9162.82 | H56: =SUM(H5:H55) -> 1634.77 | I56: =SUM(I5:I55) -> 6182.04 | J56: =SUM(J5:J55) -> 7172.52
A57: Anzahl Bestellungen | B57: =COUNTA(A5:A55) -> 51
A58: davon über Partner | B58: =COUNTIF(B5:B55,"Ja") -> 36
A59: Bestellungen, die bei Halloween mehr gekostet hätten | B59: =SUMPRODUCT((G5:G55>E5:E55+0.05)*1) -> 25
A60: Hinweis: „aufgefüllt“ = Kunden mit 1–2 Aktions-Flaschen nehmen so viele dazu, dass es 3 sind (Annahme: zusätzliche Flaschen Retatrutide 10 mg).
